[
    {
        "_id":"6810073f6aa7cd474293f38c",
        "Nombre":"Bennett Inc",
        "List_Rese\u00f1a":[

        ],
        "Calificaci\u00f3n":1,
        "Ubicaci\u00f3n":{
            "address":"756 Eric Walk Apt. 598\nDavidberg, IA 16198",
            "coordinates":[
                -109.5090150555,
                71.8092708554
            ]
        },
        "Foto_ubicaci\u00f3n":null,
        "Foto_referencia":null,
        "Estilo":[
            "Japanese",
            "Japanese"
        ],
        "Hora_apertura":"06:00:00",
        "Hora_cierre":"23:00:00"
    },
    {
        "_id":"6810073f6aa7cd474293f38d",
        "Nombre":"Taylor Group",
        "List_Rese\u00f1a":[

        ],
        "Calificaci\u00f3n":5,
        "Ubicaci\u00f3n":{
            "address":"839 Kathryn River\nWest Emilyport, KS 89399",
            "coordinates":[
                130.6760579258,
                43.500016131
            ]
        },
        "Foto_ubicaci\u00f3n":null,
        "Foto_referencia":null,
        "Estilo":[
            "American"
        ],
        "Hora_apertura":"06:00:00",
        "Hora_cierre":"23:00:00"
    },
    {
        "_id":"6810073f6aa7cd474293f38e",
        "Nombre":"Peters-Moreno",
        "List_Rese\u00f1a":[

        ],
        "Calificaci\u00f3n":2,
        "Ubicaci\u00f3n":{
            "address":"71489 Sharon Islands\nWest Christopher, CA 43470",
            "coordinates":[
                165.1387745305,
                68.8041035734
            ]
        },
        "Foto_ubicaci\u00f3n":null,
        "Foto_referencia":null,
        "Estilo":[
            "Vegan"
        ],
        "Hora_apertura":"06:00:00",
        "Hora_cierre":"23:00:00"
    },
    {
        "_id":"6810073f6aa7cd474293f38f",
        "Nombre":"King, Hoover and Martin",
        "List_Rese\u00f1a":[

        ],
        "Calificaci\u00f3n":3,
        "Ubicaci\u00f3n":{
            "address":"USS Williams\nFPO AP 85501",
            "coordinates":[
                116.6584849445,
                79.0957655932
            ]
        },
        "Foto_ubicaci\u00f3n":null,
        "Foto_referencia":null,
        "Estilo":[
            "Barbecue"
        ],
        "Hora_apertura":"06:00:00",
        "Hora_cierre":"23:00:00"
    },
    {
        "_id":"6810073f6aa7cd474293f390",
        "Nombre":"Hall-Marsh",
        "List_Rese\u00f1a":[

        ],
        "Calificaci\u00f3n":2,
        "Ubicaci\u00f3n":{
            "address":"118 Steven Haven Suite 845\nWest Rose, MS 20499",
            "coordinates":[
                173.726549547,
                -57.6804631615
            ]
        },
        "Foto_ubicaci\u00f3n":null,
        "Foto_referencia":null,
        "Estilo":[
            "Sushi"
        ],
        "Hora_apertura":"06:00:00",
        "Hora_cierre":"23:00:00"
    },
    {
        "_id":"6810073f6aa7cd474293f391",
        "Nombre":"Burton-Jones",
        "List_Rese\u00f1a":[

        ],
        "Calificaci\u00f3n":3,
        "Ubicaci\u00f3n":{
            "address":"USNV Roberts\nFPO AA 60130",
            "coordinates":[
                -9.1510692716,
                75.3392868581
            ]
        },
        "Foto_ubicaci\u00f3n":null,
        "Foto_referencia":null,
        "Estilo":[
            "Spanish",
            "Indian"
        ],
        "Hora_apertura":"06:00:00",
        "Hora_cierre":"23:00:00"
    },
    {
        "_id":"6810073f6aa7cd474293f392",
        "Nombre":"Elliott Group",
        "List_Rese\u00f1a":[

        ],
        "Calificaci\u00f3n":4,
        "Ubicaci\u00f3n":{
            "address":"12932 Delacruz Pines Apt. 553\nNew Heather, OH 29676",
            "coordinates":[
                85.1926036212,
                -17.9173516591
            ]
        },
        "Foto_ubicaci\u00f3n":null,
        "Foto_referencia":null,
        "Estilo":[
            "Mexican",
            "Japanese"
        ],
        "Hora_apertura":"06:00:00",
        "Hora_cierre":"23:00:00"
    },
    {
        "_id":"6810073f6aa7cd474293f393",
        "Nombre":"Rice and Sons",
        "List_Rese\u00f1a":[

        ],
        "Calificaci\u00f3n":4,
        "Ubicaci\u00f3n":{
            "address":"2685 Lance Radial\nLake Meganmouth, CO 28093",
            "coordinates":[
                -10.2070545789,
                83.6875348007
            ]
        },
        "Foto_ubicaci\u00f3n":null,
        "Foto_referencia":null,
        "Estilo":[
            "Vegan",
            "Lebanese"
        ],
        "Hora_apertura":"06:00:00",
        "Hora_cierre":"23:00:00"
    },
    {
        "_id":"6810073f6aa7cd474293f394",
        "Nombre":"Johnson, Young and Davis",
        "List_Rese\u00f1a":[

        ],
        "Calificaci\u00f3n":5,
        "Ubicaci\u00f3n":{
            "address":"3622 Wagner Trail Suite 592\nWest Michelleland, MP 90625",
            "coordinates":[
                169.7709667228,
                39.5539695844
            ]
        },
        "Foto_ubicaci\u00f3n":null,
        "Foto_referencia":null,
        "Estilo":[
            "Indian",
            "Indian"
        ],
        "Hora_apertura":"06:00:00",
        "Hora_cierre":"23:00:00"
    },
    {
        "_id":"6810073f6aa7cd474293f395",
        "Nombre":"Pacheco, Carpenter and Choi",
        "List_Rese\u00f1a":[

        ],
        "Calificaci\u00f3n":2,
        "Ubicaci\u00f3n":{
            "address":"52745 Derek Stravenue\nScottton, AL 50497",
            "coordinates":[
                114.3478194709,
                59.2087526523
            ]
        },
        "Foto_ubicaci\u00f3n":null,
        "Foto_referencia":null,
        "Estilo":[
            "Seafood"
        ],
        "Hora_apertura":"06:00:00",
        "Hora_cierre":"23:00:00"
    },
    {
        "_id":"6810073f6aa7cd474293f396",
        "Nombre":"Moore PLC",
        "List_Rese\u00f1a":[

        ],
        "Calificaci\u00f3n":5,
        "Ubicaci\u00f3n":{
            "address":"25647 Tristan Circles Apt. 411\nParsonstown, ND 14452",
            "coordinates":[
                -145.6444046669,
                -27.3787051838
            ]
        },
        "Foto_ubicaci\u00f3n":null,
        "Foto_referencia":null,
        "Estilo":[
            "Lebanese",
            "Italian"
        ],
        "Hora_apertura":"06:00:00",
        "Hora_cierre":"23:00:00"
    },
    {
        "_id":"6810073f6aa7cd474293f397",
        "Nombre":"Russell-Murphy",
        "List_Rese\u00f1a":[

        ],
        "Calificaci\u00f3n":4,
        "Ubicaci\u00f3n":{
            "address":"0614 Kevin Turnpike Apt. 098\nSouth Christinebury, LA 65286",
            "coordinates":[
                98.8614671051,
                -63.957893739
            ]
        },
        "Foto_ubicaci\u00f3n":null,
        "Foto_referencia":null,
        "Estilo":[
            "Barbecue"
        ],
        "Hora_apertura":"06:00:00",
        "Hora_cierre":"23:00:00"
    },
    {
        "_id":"6810073f6aa7cd474293f398",
        "Nombre":"Young-Hudson",
        "List_Rese\u00f1a":[

        ],
        "Calificaci\u00f3n":1,
        "Ubicaci\u00f3n":{
            "address":"0046 Justin Mount Apt. 928\nPort David, VI 80306",
            "coordinates":[
                90.6780136535,
                56.917452501
            ]
        },
        "Foto_ubicaci\u00f3n":null,
        "Foto_referencia":null,
        "Estilo":[
            "Seafood"
        ],
        "Hora_apertura":"06:00:00",
        "Hora_cierre":"23:00:00"
    },
    {
        "_id":"6810073f6aa7cd474293f399",
        "Nombre":"Black PLC",
        "List_Rese\u00f1a":[

        ],
        "Calificaci\u00f3n":4,
        "Ubicaci\u00f3n":{
            "address":"6962 Green Mountains\nEast William, HI 31739",
            "coordinates":[
                -174.1894194062,
                -66.0294036821
            ]
        },
        "Foto_ubicaci\u00f3n":null,
        "Foto_referencia":null,
        "Estilo":[
            "Mexican",
            "Japanese"
        ],
        "Hora_apertura":"06:00:00",
        "Hora_cierre":"23:00:00"
    },
    {
        "_id":"6810073f6aa7cd474293f39a",
        "Nombre":"Montes-Miller",
        "List_Rese\u00f1a":[

        ],
        "Calificaci\u00f3n":4,
        "Ubicaci\u00f3n":{
            "address":"7519 Berry Estate\nRamirezland, WY 89680",
            "coordinates":[
                9.7272797732,
                5.9494592301
            ]
        },
        "Foto_ubicaci\u00f3n":null,
        "Foto_referencia":null,
        "Estilo":[
            "Mediterranean"
        ],
        "Hora_apertura":"06:00:00",
        "Hora_cierre":"23:00:00"
    },
    {
        "_id":"6810073f6aa7cd474293f39b",
        "Nombre":"Washington-Anderson",
        "List_Rese\u00f1a":[

        ],
        "Calificaci\u00f3n":2,
        "Ubicaci\u00f3n":{
            "address":"169 Wagner Station Suite 655\nGonzalezshire, MH 37328",
            "coordinates":[
                32.0106740216,
                46.8198142929
            ]
        },
        "Foto_ubicaci\u00f3n":null,
        "Foto_referencia":null,
        "Estilo":[
            "Seafood"
        ],
        "Hora_apertura":"06:00:00",
        "Hora_cierre":"23:00:00"
    },
    {
        "_id":"6810073f6aa7cd474293f39c",
        "Nombre":"Rhodes-Simpson",
        "List_Rese\u00f1a":[

        ],
        "Calificaci\u00f3n":2,
        "Ubicaci\u00f3n":{
            "address":"8063 Ashley Trafficway Apt. 591\nJosephfurt, MO 89318",
            "coordinates":[
                -73.7433591878,
                58.1893794972
            ]
        },
        "Foto_ubicaci\u00f3n":null,
        "Foto_referencia":null,
        "Estilo":[
            "Spanish"
        ],
        "Hora_apertura":"06:00:00",
        "Hora_cierre":"23:00:00"
    },
    {
        "_id":"6810073f6aa7cd474293f39d",
        "Nombre":"Frank PLC",
        "List_Rese\u00f1a":[

        ],
        "Calificaci\u00f3n":4,
        "Ubicaci\u00f3n":{
            "address":"81645 Wilkerson Circle Suite 339\nNew Thomasfurt, ME 96908",
            "coordinates":[
                -54.4505184527,
                -81.0625450889
            ]
        },
        "Foto_ubicaci\u00f3n":null,
        "Foto_referencia":null,
        "Estilo":[
            "Mexican"
        ],
        "Hora_apertura":"06:00:00",
        "Hora_cierre":"23:00:00"
    },
    {
        "_id":"6810073f6aa7cd474293f39e",
        "Nombre":"Williams PLC",
        "List_Rese\u00f1a":[

        ],
        "Calificaci\u00f3n":2,
        "Ubicaci\u00f3n":{
            "address":"67106 Allen Coves\nRamosside, PR 08529",
            "coordinates":[
                -18.5543766561,
                26.6997589293
            ]
        },
        "Foto_ubicaci\u00f3n":null,
        "Foto_referencia":null,
        "Estilo":[
            "French"
        ],
        "Hora_apertura":"06:00:00",
        "Hora_cierre":"23:00:00"
    },
    {
        "_id":"6810073f6aa7cd474293f39f",
        "Nombre":"Robinson and Sons",
        "List_Rese\u00f1a":[

        ],
        "Calificaci\u00f3n":2,
        "Ubicaci\u00f3n":{
            "address":"3385 Linda Fords\nNew Lauren, FL 34276",
            "coordinates":[
                -161.2798080552,
                79.4440735072
            ]
        },
        "Foto_ubicaci\u00f3n":null,
        "Foto_referencia":null,
        "Estilo":[
            "French",
            "Seafood"
        ],
        "Hora_apertura":"06:00:00",
        "Hora_cierre":"23:00:00"
    },
    {
        "_id":"6810073f6aa7cd474293f3a0",
        "Nombre":"Morris Ltd",
        "List_Rese\u00f1a":[

        ],
        "Calificaci\u00f3n":4,
        "Ubicaci\u00f3n":{
            "address":"733 Samuel Brook\nWest Richardbury, NH 48600",
            "coordinates":[
                119.2396810331,
                -50.885006561
            ]
        },
        "Foto_ubicaci\u00f3n":null,
        "Foto_referencia":null,
        "Estilo":[
            "Japanese"
        ],
        "Hora_apertura":"06:00:00",
        "Hora_cierre":"23:00:00"
    },
    {
        "_id":"6810073f6aa7cd474293f3a1",
        "Nombre":"Fox-Wood",
        "List_Rese\u00f1a":[

        ],
        "Calificaci\u00f3n":2,
        "Ubicaci\u00f3n":{
            "address":"9412 Klein Ridge Suite 931\nNicholasbury, MI 08063",
            "coordinates":[
                123.5160738223,
                56.2790370412
            ]
        },
        "Foto_ubicaci\u00f3n":null,
        "Foto_referencia":null,
        "Estilo":[
            "Chinese"
        ],
        "Hora_apertura":"06:00:00",
        "Hora_cierre":"23:00:00"
    },
    {
        "_id":"6810073f6aa7cd474293f3a2",
        "Nombre":"Gonzalez, Bean and Sims",
        "List_Rese\u00f1a":[

        ],
        "Calificaci\u00f3n":2,
        "Ubicaci\u00f3n":{
            "address":"Unit 2695 Box 1814\nDPO AP 30828",
            "coordinates":[
                -55.754287459,
                77.2788034639
            ]
        },
        "Foto_ubicaci\u00f3n":null,
        "Foto_referencia":null,
        "Estilo":[
            "Mediterranean"
        ],
        "Hora_apertura":"06:00:00",
        "Hora_cierre":"23:00:00"
    },
    {
        "_id":"6810073f6aa7cd474293f3a3",
        "Nombre":"Allison, Washington and Figueroa",
        "List_Rese\u00f1a":[

        ],
        "Calificaci\u00f3n":1,
        "Ubicaci\u00f3n":{
            "address":"922 Mark Harbor Suite 676\nSmithport, VI 67625",
            "coordinates":[
                106.4495003392,
                -9.6432357725
            ]
        },
        "Foto_ubicaci\u00f3n":null,
        "Foto_referencia":null,
        "Estilo":[
            "Thai"
        ],
        "Hora_apertura":"06:00:00",
        "Hora_cierre":"23:00:00"
    },
    {
        "_id":"6810073f6aa7cd474293f3a4",
        "Nombre":"Wilkinson, Mosley and Jordan",
        "List_Rese\u00f1a":[

        ],
        "Calificaci\u00f3n":1,
        "Ubicaci\u00f3n":{
            "address":"87298 Walls Street\nLindaton, OR 77178",
            "coordinates":[
                -179.3880076571,
                -34.3451260568
            ]
        },
        "Foto_ubicaci\u00f3n":null,
        "Foto_referencia":null,
        "Estilo":[
            "Mediterranean",
            "Mexican"
        ],
        "Hora_apertura":"06:00:00",
        "Hora_cierre":"23:00:00"
    },
    {
        "_id":"6810073f6aa7cd474293f3a5",
        "Nombre":"Sullivan-Meyers",
        "List_Rese\u00f1a":[

        ],
        "Calificaci\u00f3n":2,
        "Ubicaci\u00f3n":{
            "address":"707 Hopkins Views\nDavenportland, WI 88376",
            "coordinates":[
                -152.4711922928,
                44.3318669233
            ]
        },
        "Foto_ubicaci\u00f3n":null,
        "Foto_referencia":null,
        "Estilo":[
            "Thai"
        ],
        "Hora_apertura":"06:00:00",
        "Hora_cierre":"23:00:00"
    },
    {
        "_id":"6810073f6aa7cd474293f3a6",
        "Nombre":"Lopez-Gardner",
        "List_Rese\u00f1a":[

        ],
        "Calificaci\u00f3n":4,
        "Ubicaci\u00f3n":{
            "address":"3526 Kenneth Cove\nWest Brenda, KS 09033",
            "coordinates":[
                102.5039310261,
                76.2482766706
            ]
        },
        "Foto_ubicaci\u00f3n":null,
        "Foto_referencia":null,
        "Estilo":[
            "Indian",
            "Barbecue"
        ],
        "Hora_apertura":"06:00:00",
        "Hora_cierre":"23:00:00"
    },
    {
        "_id":"6810073f6aa7cd474293f3a7",
        "Nombre":"Greer, Wells and Willis",
        "List_Rese\u00f1a":[

        ],
        "Calificaci\u00f3n":2,
        "Ubicaci\u00f3n":{
            "address":"489 Cindy Street\nNew Brooke, NJ 24082",
            "coordinates":[
                78.7332841657,
                19.9987615542
            ]
        },
        "Foto_ubicaci\u00f3n":null,
        "Foto_referencia":null,
        "Estilo":[
            "Lebanese"
        ],
        "Hora_apertura":"06:00:00",
        "Hora_cierre":"23:00:00"
    },
    {
        "_id":"6810073f6aa7cd474293f3a8",
        "Nombre":"Campbell-Gonzales",
        "List_Rese\u00f1a":[

        ],
        "Calificaci\u00f3n":2,
        "Ubicaci\u00f3n":{
            "address":"064 Haynes Points Suite 141\nNew Terrychester, NV 91604",
            "coordinates":[
                102.7403055918,
                -10.3749235497
            ]
        },
        "Foto_ubicaci\u00f3n":null,
        "Foto_referencia":null,
        "Estilo":[
            "French"
        ],
        "Hora_apertura":"06:00:00",
        "Hora_cierre":"23:00:00"
    },
    {
        "_id":"6810073f6aa7cd474293f3a9",
        "Nombre":"Gonzales Inc",
        "List_Rese\u00f1a":[

        ],
        "Calificaci\u00f3n":5,
        "Ubicaci\u00f3n":{
            "address":"USNS Hampton\nFPO AP 73834",
            "coordinates":[
                47.8890608192,
                54.3580421916
            ]
        },
        "Foto_ubicaci\u00f3n":null,
        "Foto_referencia":null,
        "Estilo":[
            "Vegan",
            "Thai"
        ],
        "Hora_apertura":"06:00:00",
        "Hora_cierre":"23:00:00"
    },
    {
        "_id":"6810073f6aa7cd474293f3aa",
        "Nombre":"Shelton-Gregory",
        "List_Rese\u00f1a":[

        ],
        "Calificaci\u00f3n":4,
        "Ubicaci\u00f3n":{
            "address":"3574 Zachary Pine Apt. 326\nSouth Kellyside, SC 59032",
            "coordinates":[
                -136.6123913422,
                -50.3804576272
            ]
        },
        "Foto_ubicaci\u00f3n":null,
        "Foto_referencia":null,
        "Estilo":[
            "Thai",
            "Spanish"
        ],
        "Hora_apertura":"06:00:00",
        "Hora_cierre":"23:00:00"
    },
    {
        "_id":"6810073f6aa7cd474293f3ab",
        "Nombre":"Stewart-Richardson",
        "List_Rese\u00f1a":[

        ],
        "Calificaci\u00f3n":5,
        "Ubicaci\u00f3n":{
            "address":"89023 Padilla Manor Suite 791\nRiveraton, WI 87675",
            "coordinates":[
                -57.8780794316,
                52.8958197935
            ]
        },
        "Foto_ubicaci\u00f3n":null,
        "Foto_referencia":null,
        "Estilo":[
            "Mediterranean"
        ],
        "Hora_apertura":"06:00:00",
        "Hora_cierre":"23:00:00"
    },
    {
        "_id":"6810073f6aa7cd474293f3ac",
        "Nombre":"Carter, Anderson and Gordon",
        "List_Rese\u00f1a":[

        ],
        "Calificaci\u00f3n":2,
        "Ubicaci\u00f3n":{
            "address":"0098 Lisa Lodge\nLake Amanda, ID 33225",
            "coordinates":[
                30.3999771921,
                11.3604444779
            ]
        },
        "Foto_ubicaci\u00f3n":null,
        "Foto_referencia":null,
        "Estilo":[
            "Vegan"
        ],
        "Hora_apertura":"06:00:00",
        "Hora_cierre":"23:00:00"
    },
    {
        "_id":"6810073f6aa7cd474293f3ad",
        "Nombre":"Smith and Sons",
        "List_Rese\u00f1a":[

        ],
        "Calificaci\u00f3n":3,
        "Ubicaci\u00f3n":{
            "address":"915 Brian Mews Apt. 438\nJasminemouth, NE 06142",
            "coordinates":[
                -71.0494209695,
                23.4883900811
            ]
        },
        "Foto_ubicaci\u00f3n":null,
        "Foto_referencia":null,
        "Estilo":[
            "Chinese",
            "Mexican"
        ],
        "Hora_apertura":"06:00:00",
        "Hora_cierre":"23:00:00"
    },
    {
        "_id":"6810073f6aa7cd474293f3ae",
        "Nombre":"Neal, Torres and Shaffer",
        "List_Rese\u00f1a":[

        ],
        "Calificaci\u00f3n":2,
        "Ubicaci\u00f3n":{
            "address":"7042 Hannah Park\nSouth Jasminetown, NM 27212",
            "coordinates":[
                -106.5006699799,
                75.2567787884
            ]
        },
        "Foto_ubicaci\u00f3n":null,
        "Foto_referencia":null,
        "Estilo":[
            "Spanish",
            "Barbecue"
        ],
        "Hora_apertura":"06:00:00",
        "Hora_cierre":"23:00:00"
    },
    {
        "_id":"6810073f6aa7cd474293f3af",
        "Nombre":"Bennett-Chapman",
        "List_Rese\u00f1a":[

        ],
        "Calificaci\u00f3n":1,
        "Ubicaci\u00f3n":{
            "address":"12528 Bill Bridge Apt. 248\nNorth Michael, IL 92096",
            "coordinates":[
                34.3443682061,
                68.0855831586
            ]
        },
        "Foto_ubicaci\u00f3n":null,
        "Foto_referencia":null,
        "Estilo":[
            "Chinese"
        ],
        "Hora_apertura":"06:00:00",
        "Hora_cierre":"23:00:00"
    },
    {
        "_id":"6810073f6aa7cd474293f3b0",
        "Nombre":"Spears-Davis",
        "List_Rese\u00f1a":[

        ],
        "Calificaci\u00f3n":4,
        "Ubicaci\u00f3n":{
            "address":"27592 Brian Burgs\nNew Ryanton, FL 80560",
            "coordinates":[
                -164.9578165994,
                -10.0251566653
            ]
        },
        "Foto_ubicaci\u00f3n":null,
        "Foto_referencia":null,
        "Estilo":[
            "Indian",
            "Japanese"
        ],
        "Hora_apertura":"06:00:00",
        "Hora_cierre":"23:00:00"
    },
    {
        "_id":"6810073f6aa7cd474293f3b1",
        "Nombre":"Wilson, Ballard and Davis",
        "List_Rese\u00f1a":[

        ],
        "Calificaci\u00f3n":4,
        "Ubicaci\u00f3n":{
            "address":"419 Jones Crossroad\nEast Edwardtown, MT 76607",
            "coordinates":[
                -93.9895993067,
                4.5157039427
            ]
        },
        "Foto_ubicaci\u00f3n":null,
        "Foto_referencia":null,
        "Estilo":[
            "Vegan"
        ],
        "Hora_apertura":"06:00:00",
        "Hora_cierre":"23:00:00"
    },
    {
        "_id":"6810073f6aa7cd474293f3b2",
        "Nombre":"Hunter LLC",
        "List_Rese\u00f1a":[

        ],
        "Calificaci\u00f3n":1,
        "Ubicaci\u00f3n":{
            "address":"622 Smith Curve\nNew Feliciaside, NE 30922",
            "coordinates":[
                161.0354413837,
                7.2134627779
            ]
        },
        "Foto_ubicaci\u00f3n":null,
        "Foto_referencia":null,
        "Estilo":[
            "Barbecue",
            "Sushi"
        ],
        "Hora_apertura":"06:00:00",
        "Hora_cierre":"23:00:00"
    },
    {
        "_id":"6810073f6aa7cd474293f3b3",
        "Nombre":"Moore-Wilson",
        "List_Rese\u00f1a":[

        ],
        "Calificaci\u00f3n":1,
        "Ubicaci\u00f3n":{
            "address":"558 Aguilar Pine Apt. 666\nMariahtown, AL 67120",
            "coordinates":[
                120.2443107037,
                -78.4880313628
            ]
        },
        "Foto_ubicaci\u00f3n":null,
        "Foto_referencia":null,
        "Estilo":[
            "Lebanese"
        ],
        "Hora_apertura":"06:00:00",
        "Hora_cierre":"23:00:00"
    },
    {
        "_id":"6810073f6aa7cd474293f3b4",
        "Nombre":"Thompson Ltd",
        "List_Rese\u00f1a":[

        ],
        "Calificaci\u00f3n":2,
        "Ubicaci\u00f3n":{
            "address":"144 Loretta Landing\nLake Richard, OH 28939",
            "coordinates":[
                150.5594274134,
                37.8712918851
            ]
        },
        "Foto_ubicaci\u00f3n":null,
        "Foto_referencia":null,
        "Estilo":[
            "Barbecue",
            "Barbecue"
        ],
        "Hora_apertura":"06:00:00",
        "Hora_cierre":"23:00:00"
    },
    {
        "_id":"6810073f6aa7cd474293f3b5",
        "Nombre":"Smith PLC",
        "List_Rese\u00f1a":[

        ],
        "Calificaci\u00f3n":5,
        "Ubicaci\u00f3n":{
            "address":"1542 Nguyen Creek\nMasonmouth, IA 87708",
            "coordinates":[
                -1.594405245,
                -31.9596658808
            ]
        },
        "Foto_ubicaci\u00f3n":null,
        "Foto_referencia":null,
        "Estilo":[
            "Vegan",
            "Thai"
        ],
        "Hora_apertura":"06:00:00",
        "Hora_cierre":"23:00:00"
    },
    {
        "_id":"6810073f6aa7cd474293f3b6",
        "Nombre":"Robertson, Thomas and Adams",
        "List_Rese\u00f1a":[

        ],
        "Calificaci\u00f3n":4,
        "Ubicaci\u00f3n":{
            "address":"579 Henry Ways Suite 664\nMelissaland, NE 70188",
            "coordinates":[
                -11.3982009921,
                36.4766540802
            ]
        },
        "Foto_ubicaci\u00f3n":null,
        "Foto_referencia":null,
        "Estilo":[
            "Lebanese",
            "Mexican"
        ],
        "Hora_apertura":"06:00:00",
        "Hora_cierre":"23:00:00"
    },
    {
        "_id":"6810073f6aa7cd474293f3b7",
        "Nombre":"Gonzalez, Soto and Levine",
        "List_Rese\u00f1a":[

        ],
        "Calificaci\u00f3n":2,
        "Ubicaci\u00f3n":{
            "address":"14429 James Club\nNew Justinshire, NE 19978",
            "coordinates":[
                -158.4701219499,
                75.685725886
            ]
        },
        "Foto_ubicaci\u00f3n":null,
        "Foto_referencia":null,
        "Estilo":[
            "Seafood",
            "Sushi"
        ],
        "Hora_apertura":"06:00:00",
        "Hora_cierre":"23:00:00"
    },
    {
        "_id":"6810073f6aa7cd474293f3b8",
        "Nombre":"Frye LLC",
        "List_Rese\u00f1a":[

        ],
        "Calificaci\u00f3n":2,
        "Ubicaci\u00f3n":{
            "address":"Unit 0118 Box 1446\nDPO AA 18535",
            "coordinates":[
                133.3895725606,
                -63.8701869603
            ]
        },
        "Foto_ubicaci\u00f3n":null,
        "Foto_referencia":null,
        "Estilo":[
            "Italian"
        ],
        "Hora_apertura":"06:00:00",
        "Hora_cierre":"23:00:00"
    },
    {
        "_id":"6810073f6aa7cd474293f3b9",
        "Nombre":"Ellis PLC",
        "List_Rese\u00f1a":[

        ],
        "Calificaci\u00f3n":3,
        "Ubicaci\u00f3n":{
            "address":"PSC 8959, Box 6062\nAPO AE 95225",
            "coordinates":[
                -173.3050649939,
                -64.8627380965
            ]
        },
        "Foto_ubicaci\u00f3n":null,
        "Foto_referencia":null,
        "Estilo":[
            "Barbecue",
            "Vegan"
        ],
        "Hora_apertura":"06:00:00",
        "Hora_cierre":"23:00:00"
    },
    {
        "_id":"6810073f6aa7cd474293f3ba",
        "Nombre":"Vega and Sons",
        "List_Rese\u00f1a":[

        ],
        "Calificaci\u00f3n":4,
        "Ubicaci\u00f3n":{
            "address":"13827 Sanchez Stream\nHernandezbury, AZ 92491",
            "coordinates":[
                28.4209654525,
                44.5576736394
            ]
        },
        "Foto_ubicaci\u00f3n":null,
        "Foto_referencia":null,
        "Estilo":[
            "Chinese"
        ],
        "Hora_apertura":"06:00:00",
        "Hora_cierre":"23:00:00"
    },
    {
        "_id":"6810073f6aa7cd474293f3bb",
        "Nombre":"Jackson-Clark",
        "List_Rese\u00f1a":[

        ],
        "Calificaci\u00f3n":1,
        "Ubicaci\u00f3n":{
            "address":"99583 Davis Plaza\nHernandezbury, TX 20672",
            "coordinates":[
                -12.1923158188,
                26.9592750065
            ]
        },
        "Foto_ubicaci\u00f3n":null,
        "Foto_referencia":null,
        "Estilo":[
            "Mediterranean"
        ],
        "Hora_apertura":"06:00:00",
        "Hora_cierre":"23:00:00"
    },
    {
        "_id":"6810073f6aa7cd474293f3bc",
        "Nombre":"Perez-Colon",
        "List_Rese\u00f1a":[

        ],
        "Calificaci\u00f3n":1,
        "Ubicaci\u00f3n":{
            "address":"Unit 1189 Box 4905\nDPO AP 21223",
            "coordinates":[
                137.7389823719,
                5.271113303
            ]
        },
        "Foto_ubicaci\u00f3n":null,
        "Foto_referencia":null,
        "Estilo":[
            "American",
            "Italian"
        ],
        "Hora_apertura":"06:00:00",
        "Hora_cierre":"23:00:00"
    },
    {
        "_id":"6810073f6aa7cd474293f3bd",
        "Nombre":"Bailey, Evans and Jones",
        "List_Rese\u00f1a":[

        ],
        "Calificaci\u00f3n":3,
        "Ubicaci\u00f3n":{
            "address":"119 Avila Place\nPort Robert, IA 05171",
            "coordinates":[
                -160.2012369343,
                8.1766226964
            ]
        },
        "Foto_ubicaci\u00f3n":null,
        "Foto_referencia":null,
        "Estilo":[
            "Mediterranean"
        ],
        "Hora_apertura":"06:00:00",
        "Hora_cierre":"23:00:00"
    }
]